README.md
setup.py
hthworldwide/__init__.py
hthworldwide/api.py
hthworldwide/data.py
hthworldwide.egg-info/PKG-INFO
hthworldwide.egg-info/SOURCES.txt
hthworldwide.egg-info/dependency_links.txt
hthworldwide.egg-info/not-zip-safe
hthworldwide.egg-info/requires.txt
hthworldwide.egg-info/top_level.txt