Metadata-Version: 2.1
Name: hthworldwide
Version: 0.0.2
Summary: HTH World Wide Medical Facilities Database controller.
Home-page: https://gitlab.com/wefindx/hthworldwide
Author: Mindey
Author-email: mindey@qq.com
License: ASK FOR PERMISSIONS
Platform: UNKNOWN
Provides-Extra: test
